metagen/__init__.py
metagen/base.py
metagen/config.py
metagen/control.py
metagen/elements.py
metagen/generator.py
metagen/gui.py
metagen/helpers.py
metagen/importer.py
metagen/main.py
metagen/metadata.py
metagen/pipes.py
metagen/presets.py
metagen/register.py
metagen/storage.py
metagen/utils.py
metagen/components/__init__.py
metagen/components/_base.py
metagen/components/_general.py
metagen/components/_map.py
metagen/components/_timeline.py
metagen/components/_view.py
metagen/config/__init__.py
metagen/config/cli.py
metagen/config/config.py
metagen/config/config.yaml
metagen/utils/__init__.py
metagen/utils/geometry.py
metagen/utils/parser.py
ptrmetagen-1.3.0.dist-info/METADATA
ptrmetagen-1.3.0.dist-info/WHEEL
ptrmetagen-1.3.0.dist-info/entry_points.txt
ptrmetagen-1.3.0.dist-info/top_level.txt
ptrmetagen-1.3.0.dist-info/RECORD
