Metadata-Version: 2.1
Name: ptrmetagen
Version: 1.3.0
Summary: Package for generation of metastructures for Panter project
Home-page: https://github.com/gisat-panther/ptr-metagen
Author: Michal Opletal
Author-email: michal.opletal@gisat.cz
License: MIT
Platform: UNKNOWN
Classifier: License :: OSI Approved :: MIT License
Classifier: Programming Language :: Python :: 3
Classifier: Programming Language :: Python :: 3.9
Requires-Dist: pytest (==7.2.0)
Requires-Dist: pydantic (==1.9.1)
Requires-Dist: setuptools (==58.5.3)
Requires-Dist: Shapely (==1.8.1)
Requires-Dist: PyYAML (==5.4.1)
Requires-Dist: click (==7.1.2)
Requires-Dist: pandas (==1.4.3)
Requires-Dist: requests (==2.28.1)
